crackqcli
