Metadata-Version: 1.0
Name: crackqcli
Version: 0.4.1
Summary: Hashcrack Crackq command-line client
Home-page: http://hashcrack.org
Author: Hashcrack
Author-email: support@hashcrack.org
License: GPLv3
Keywords: hashcrack crackq password bruteforce hash NTLM MD5 SHA1 WPA WPA2 DESCRYPT MD5CRYPT PDF Wordpress Joomla phpBB3 MYSQL
Platform: UNKNOWN
